polymorphology/__init__.py
polymorphology/config.txt
polymorphology/features.py
polymorphology-0.0.1.dist-info/METADATA
polymorphology-0.0.1.dist-info/WHEEL
polymorphology-0.0.1.dist-info/licenses/LICENSE
polymorphology-0.0.1.dist-info/RECORD
